{"name":"diaries","type":"base","schema":[{"system":false,"id":"dy_sp","name":"space_id","type":"relation","required":true,"options":{"collectionId":"couple_spaces","cascadeDelete":true,"maxSelect":1}},{"system":false,"id":"dy_ui","name":"user_id","type":"text","required":true,"options":{"min":null,"max":null,"pattern":""}},{"system":false,"id":"dy_ct","name":"category","type":"select","required":false,"options":{"values":["daily","anniversary","mood"],"maxSelect":1}},{"system":false,"id":"dy_tl","name":"title","type":"text","required":true,"options":{"min":null,"max":200,"pattern":""}},{"system":false,"id":"dy_cn","name":"content","type":"text","required":true,"options":{"min":null,"max":5000,"pattern":""}},{"system":false,"id":"dy_im","name":"images","type":"json","required":false,"options":{}},{"system":false,"id":"dy_lc","name":"likes_count","type":"number","required":false,"options":{"min":0,"max":null}},{"system":false,"id":"dy_dl","name":"deleted","type":"bool","required":false,"options":{}}],"listRule":"(space_id.user_a_id = @request.auth.id || space_id.user_b_id = @request.auth.id) && deleted = false","viewRule":"space_id.user_a_id = @request.auth.id || space_id.user_b_id = @request.auth.id","createRule":"@request.auth.id != ''","updateRule":"user_id = @request.auth.id","deleteRule":"user_id = @request.auth.id"}
